flink_agents/__init__.py
flink_agents/api/__init__.py
flink_agents/api/agent.py
flink_agents/api/chat_message.py
flink_agents/api/configuration.py
flink_agents/api/core_options.py
flink_agents/api/decorators.py
flink_agents/api/execution_environment.py
flink_agents/api/memory_object.py
flink_agents/api/memory_reference.py
flink_agents/api/metric_group.py
flink_agents/api/resource.py
flink_agents/api/runner_context.py
flink_agents/api/agents/__init__.py
flink_agents/api/agents/react_agent.py
flink_agents/api/agents/tests/__init__.py
flink_agents/api/agents/tests/test_row_schema.py
flink_agents/api/chat_models/__init__.py
flink_agents/api/chat_models/chat_model.py
flink_agents/api/embedding_models/__init__.py
flink_agents/api/embedding_models/embedding_model.py
flink_agents/api/events/__init__.py
flink_agents/api/events/chat_event.py
flink_agents/api/events/context_retrieval_event.py
flink_agents/api/events/event.py
flink_agents/api/events/tool_event.py
flink_agents/api/prompts/__init__.py
flink_agents/api/prompts/prompt.py
flink_agents/api/prompts/utils.py
flink_agents/api/tests/__init__.py
flink_agents/api/tests/test_decorators.py
flink_agents/api/tests/test_event.py
flink_agents/api/tests/test_prompt.py
flink_agents/api/tests/test_tool.py
flink_agents/api/tests/mcp/__init__.py
flink_agents/api/tests/mcp/mcp_server.py
flink_agents/api/tests/mcp/test_mcp.py
flink_agents/api/tools/__init__.py
flink_agents/api/tools/mcp.py
flink_agents/api/tools/tool.py
flink_agents/api/tools/utils.py
flink_agents/api/vector_stores/__init__.py
flink_agents/api/vector_stores/vector_store.py
flink_agents/e2e_tests/__init__.py
flink_agents/e2e_tests/agent_example.py
flink_agents/e2e_tests/chat_model_example.py
flink_agents/e2e_tests/common_tools.py
flink_agents/e2e_tests/from_datastream_to_table.py
flink_agents/e2e_tests/integrate_datastream_with_agent_example.py
flink_agents/e2e_tests/integrate_table_with_agent_example.py
flink_agents-0.1.1.dist-info/licenses/LICENSE
flink_agents-0.1.1.dist-info/METADATA
flink_agents-0.1.1.dist-info/WHEEL
flink_agents-0.1.1.dist-info/top_level.txt
flink_agents-0.1.1.dist-info/RECORD
