Metadata-Version: 2.4
Name: flink-agents
Version: 0.1.1
Summary: Flink Agents Python API
Author-email: Apache Software Foundation <dev@flink.apache.org>
Classifier: Development Status :: 5 - Production/Stable
Classifier: Programming Language :: Python :: 3.10
Classifier: Programming Language :: Python :: 3.11
Requires-Python: <3.12,>=3.10
License-File: LICENSE
Requires-Dist: apache-flink==1.20.3
Requires-Dist: pydantic==2.11.4
Requires-Dist: docstring-parser==0.16
Requires-Dist: pyyaml==6.0.2
Requires-Dist: mcp>=1.8.0
Requires-Dist: setuptools>=75.3
Requires-Dist: ollama==0.4.8
Requires-Dist: dashscope~=1.24.2
Requires-Dist: openai>=1.66.3
Requires-Dist: anthropic>=0.64.0
Requires-Dist: chromadb==1.0.21
Provides-Extra: dev
Requires-Dist: flink-agents[build]; extra == "dev"
Requires-Dist: flink-agents[lint]; extra == "dev"
Requires-Dist: flink-agents[test]; extra == "dev"
Provides-Extra: build
Requires-Dist: build; extra == "build"
Provides-Extra: test
Requires-Dist: pytest==8.4.0; extra == "test"
Provides-Extra: lint
Requires-Dist: ruff==0.11.13; extra == "lint"
Dynamic: license-file
